scibd
