Metadata-Version: 2.1
Name: scibd
Version: 0.1.3
Summary: A doublet detetion tool for scCAS data. https://github.com/Ying-Lab/scIBD
Home-page: https://github.com/Ying-Lab/scIBD/
Author: Wenhao Zhang
Author-email: 23220210156258@stu.xmu.edu.cn
License: MIT
Classifier: License :: OSI Approved :: MIT License
Classifier: Programming Language :: Python
Classifier: Programming Language :: Python :: 3
Classifier: Programming Language :: Python :: 3.8
Classifier: Programming Language :: Python :: Implementation :: CPython
Classifier: Programming Language :: Python :: Implementation :: PyPy
Requires-Python: >=3.8.0
License-File: LICENSE
